rmx/__init__.py
rmx/_version.py
rmx/cli/__init__.py
rmx/cli/_config_loader.py
rmx/cli/_utils.py
rmx/cli/run.py
rmx/cli/sync.py
rmx/config.py
rmx/helpers.py
rmx/machine.py
rmx/runner.py
rmx-0.2.3.dist-info/entry_points.txt
rmx-0.2.3.dist-info/WHEEL
rmx-0.2.3.dist-info/METADATA
rmx-0.2.3.dist-info/RECORD
