Metadata-Version: 2.1
Name: rmx
Version: 0.2.3
Summary: Remote code deployment and execution for ML researchers.
License: MIT License
Author-email: Takuma Yoneda <takuma-yoneda@users.noreply.github.com>,Takuma Yoneda <takuma.ynd@gmail.com>
Requires-Python: >=3.8
Classifier: License :: OSI Approved :: MIT License
Classifier: Operating System :: MacOS
Classifier: Operating System :: POSIX
Classifier: Operating System :: Unix
Classifier: Programming Language :: Python
Classifier: Programming Language :: Python :: 3.6
Classifier: Programming Language :: Python :: 3.7
Classifier: Programming Language :: Python :: 3.8
Classifier: Programming Language :: Python :: 3.9
Requires-Dist: colorlog
Requires-Dist: docker
Requires-Dist: dockerpty>=0.4.1
Requires-Dist: fabric
Requires-Dist: pyjson5
Requires-Dist: python-dotenv
Requires-Dist: python-on-whales>=0.53.0
Requires-Dist: randomname
Requires-Dist: simple_slurm_command
Project-URL: Homepage, https://github.com/takuma-yoneda/rmx
